{
    "pools": [
      {
        "rolls": 1,
        "entries": [
          {
            "type": "minecraft:item",
            "name": "minecraft:bow",
            "functions": [
              {
                "function": "minecraft:set_count",
                "count": 1
              },
              {
                "function": "minecraft:set_name",
                "target": "item_name",
                "name": {
                  "text": "Bow",
                  "color": "green"
                }
              },
              {
                "function": "minecraft:set_lore",
                "lore": [
                  {
                    "text": "コスト: ",
                    "color": "gray",
                    "italic": false,
                    "extra": [
                      {
                        "text": "12 Gold",
                        "color": "gold",
                        "italic": false
                      }
                    ]
                  }
                ],
                "mode": "replace_all"
              },
              {
                "function": "minecraft:set_custom_data",
                "tag": "{shop:bow}"
              }
            ]
          }
        ]
      }
    ]
  }
  